[{"subject":"AFAM","number":"1101","title":"Introduction to African American and Africana Studies","scheduleType":"Lecture","credits":4,"nuPath":["DD"],"sections":[{"term":"202310","crn":"11473"}]},{"subject":"AFAM","number":"1104","title":"The African-American Experience through Music","scheduleType":"Lecture","credits":4,"nuPath":["IC"],"sections":[{"term":"202310","crn":"10938"}]},{"subject":"AFAM","number":"1225","title":"Gender, Race, and Medicine","scheduleType":"Lecture","credits":4,"nuPath":["DD"],"sections":[{"term":"202310","crn":"19055"}]},{"subject":"AFAM","number":"2296","title":"Early African-American Literature","scheduleType":"Lecture","credits":4,"nuPath":["DD","IC"],"sections":[{"term":"202310","crn":"19056"}]},{"subject":"AFAM","number":"2355","title":"Race, Identity, Social Change, and Empowerment","scheduleType":"Lecture","credits":4,"nuPath":["DD"],"sections":[{"term":"202310","crn":"16452"}]},{"subject":"AFAM","number":"3404","title":"African American Rhetorical Traditions","scheduleType":"Lecture","credits":4,"nuPath":["DD","IC"],"sections":[{"term":"202310","crn":"19058"}]}]