[{"subject":"INFO","number":"5001","title":"Application Modeling and Design","scheduleType":"Lecture","credits":4,"nuPath":[],"_termReferenceMap":{"202310":"15520"}},{"subject":"INFO","number":"5100","title":"Application Engineering and Development","scheduleType":"Lecture","credits":4,"nuPath":[],"_termReferenceMap":{"202310":"20210"}},{"subject":"INFO","number":"5101","title":"Lab for INFO 5100","scheduleType":"Lab","credits":0,"nuPath":[],"_termReferenceMap":{"202310":"20211"}},{"subject":"INFO","number":"6105","title":"Data Science Engineering Methods and Tools","scheduleType":"Lecture","credits":4,"nuPath":[],"_termReferenceMap":{"202240":"41099","202260":"61559","202310":"19098"}},{"subject":"INFO","number":"6150","title":"Web Design and User Experience Engineering","scheduleType":"Lecture","credits":4,"nuPath":[],"_termReferenceMap":{"202310":"20821"}},{"subject":"INFO","number":"6205","title":"Program Structure and Algorithms","scheduleType":"Lecture","credits":4,"nuPath":[],"_termReferenceMap":{"202310":"14206"}},{"subject":"INFO","number":"6215","title":"Business Analysis and Information Engineering","scheduleType":"Lecture","credits":4,"nuPath":[],"_termReferenceMap":{"202310":"13726"}},{"subject":"INFO","number":"6245","title":"Planning and Managing Information Systems Development","scheduleType":"Lecture","credits":4,"nuPath":[],"_termReferenceMap":{"202240":"41786","202310":"13788"}},{"subject":"INFO","number":"6250","title":"Web Development Tools and Methods","scheduleType":"Lecture","credits":4,"nuPath":[],"_termReferenceMap":{"202310":"20639"}},{"subject":"INFO","number":"6251","title":"Lab for INFO 6250","scheduleType":"Lab","credits":0,"nuPath":[],"_termReferenceMap":{"202310":"20637"}},{"subject":"INFO","number":"6255","title":"Software Quality Control and Management","scheduleType":"Lecture","credits":4,"nuPath":[],"_termReferenceMap":{"202310":"14037"}},{"subject":"INFO","number":"6350","title":"Smartphones-Based Web Development","scheduleType":"Lecture","credits":4,"nuPath":[],"_termReferenceMap":{"202310":"14235"}},{"subject":"INFO","number":"6660","title":"Business Ethics and Intellectual Property for Engineers","scheduleType":"Lecture","credits":4,"nuPath":[],"_termReferenceMap":{"202310":"13710"}},{"subject":"INFO","number":"7225","title":"Accounting and Budgetary Systems for Engineers","scheduleType":"Lecture","credits":4,"nuPath":[],"_termReferenceMap":{"202260":"61476","202310":"20918"}},{"subject":"INFO","number":"7245","title":"Agile Software Development","scheduleType":"Lecture","credits":4,"nuPath":[],"_termReferenceMap":{"202240":"41817","202310":"14620"}},{"subject":"INFO","number":"7250","title":"Engineering of Big-Data Systems","scheduleType":"Lecture","credits":4,"nuPath":[],"_termReferenceMap":{"202310":"12019"}},{"subject":"INFO","number":"7255","title":"Advanced Big-Data Applications and Indexing Techniques","scheduleType":"Lecture","credits":4,"nuPath":[],"_termReferenceMap":{"202310":"14328"}},{"subject":"INFO","number":"7260","title":"Business Process Engineering","scheduleType":"Lecture","credits":4,"nuPath":[],"_termReferenceMap":{"202260":"61432","202310":"20908"}},{"subject":"INFO","number":"7285","title":"Organizational Change and IT","scheduleType":"Lecture","credits":4,"nuPath":[],"_termReferenceMap":{"202310":"12152"}},{"subject":"INFO","number":"7374","title":"App Mach Learn &amp; Python In Fin","scheduleType":"Lecture","credits":1,"nuPath":[],"_termReferenceMap":{"202240":"40521","202310":"14621"}},{"subject":"INFO","number":"7375","title":"Special Topics in Artificial Intelligence Engineering and Applications","scheduleType":"Lecture","credits":1,"nuPath":[],"_termReferenceMap":{"202310":"14036"}},{"subject":"INFO","number":"7385","title":"Managerial Communications for Engineers","scheduleType":"Lecture","credits":4,"nuPath":[],"_termReferenceMap":{"202310":"13352"}},{"subject":"INFO","number":"7390","title":"Advances in Data Sciences and Architecture","scheduleType":"Lecture","credits":4,"nuPath":[],"_termReferenceMap":{"202310":"14623"}},{"subject":"INFO","number":"7500","title":"Cryptocurrency and Smart Contract Engineering","scheduleType":"Lecture","credits":4,"nuPath":[],"_termReferenceMap":{"202310":"14917"}},{"subject":"INFO","number":"7510","title":"Smart Contract Application Engineering and Development","scheduleType":"Lecture","credits":4,"nuPath":[],"_termReferenceMap":{"202310":"13389"}},{"subject":"INFO","number":"7520","title":"Engineering of Advanced Cryptocurrency Systems","scheduleType":"Lecture","credits":4,"nuPath":[],"_termReferenceMap":{"202260":"61433","202310":"20737"}},{"subject":"INFO","number":"7525","title":"Regulatory Aspects of Smart Contract Automation","scheduleType":"Lecture","credits":2,"nuPath":[],"_termReferenceMap":{"202310":"19101"}},{"subject":"INFO","number":"7535","title":"Digital Smart Contracts Product Innovations","scheduleType":"Lecture","credits":2,"nuPath":[],"_termReferenceMap":{"202310":"19102"}},{"subject":"INFO","number":"7610","title":"Special Topics in Natural Language Engineering Methods and Tools","scheduleType":"Lecture","credits":4,"nuPath":[],"_termReferenceMap":{"202240":"40715","202310":"14624"}},{"subject":"INFO","number":"7978","title":"Independent Study","scheduleType":"Individual Instruction","credits":1,"nuPath":[],"_termReferenceMap":{"202240":"41993","202310":"10582"}},{"subject":"INFO","number":"7990","title":"Thesis","scheduleType":"Individual Instruction","credits":1,"nuPath":[],"_termReferenceMap":{"202310":"19103"}},{"subject":"INFO","number":"7205","title":"Advanced Application Engineering Project","scheduleType":"Lecture","credits":4,"nuPath":[],"_termReferenceMap":{"202260":"61468"}}]