[{"subject":"SPNS","number":"1101","title":"Elementary Spanish 1","scheduleType":"Lecture","credits":4,"nuPath":[],"_termReferenceMap":{"202240":"40005","202310":"20587"}},{"subject":"SPNS","number":"1102","title":"Elementary Spanish 2","scheduleType":"Lecture","credits":4,"nuPath":[],"_termReferenceMap":{"202310":"20780"}},{"subject":"SPNS","number":"2101","title":"Intermediate Spanish 1","scheduleType":"Lecture","credits":4,"nuPath":[],"_termReferenceMap":{"202310":"20588"}},{"subject":"SPNS","number":"2102","title":"Intermediate Spanish 2: Becoming a Global Citizen","scheduleType":"Lecture","credits":4,"nuPath":["WI"],"_termReferenceMap":{"202240":"40761","202310":"13242"}},{"subject":"SPNS","number":"3101","title":"Advanced Spanish 1: Deconstructing Borders","scheduleType":"Lecture","credits":4,"nuPath":[],"_termReferenceMap":{"202240":"40885","202310":"20589"}},{"subject":"SPNS","number":"3102","title":"Advanced Spanish 2: Hispanic and Latinx Identity","scheduleType":"Lecture","credits":4,"nuPath":[],"_termReferenceMap":{"202310":"12923"}},{"subject":"SPNS","number":"3602","title":"Introduction to Spanish Linguistics","scheduleType":"Lecture","credits":4,"nuPath":[],"_termReferenceMap":{"202310":"19489"}},{"subject":"SPNS","number":"3603","title":"Spanish in the US","scheduleType":"Lecture","credits":4,"nuPath":[],"_termReferenceMap":{"202240":"41707","202310":"19490"}}]